{
    "from": {
        "address": "0xa0b86991c6218b36c1d19d4a2e9eb0ce3606eb48",
        "decimals": 6,
        "symbol": "USDC",
        "gas": "0"
    },
    "to": {
        "address": "0xc02aaa39b223fe8d0a0e5c4f27ead9083c756cc2",
        "decimals": 18,
        "symbol": "WETH",
        "gas": "0"
    },
    "trades": [
        {
            "input": 2000.0,
            "output": 1.0420236353150754,
            "distribution": [
                20.0,
                20.0,
                20.0,
                0.00053145,
                39.99946855
            ],
            "ratio": 0.0005210118176575376
        },
        {
            "input": 4000.0,
            "output": 2.0839666339692133,
            "distribution": [
                20.0,
                20.0,
                33.12146865,
                0.00053135,
                26.878
            ],
            "ratio": 0.0005209916584923033
        },
        {
            "input": 6000.0,
            "output": 3.125885187133189,
            "distribution": [
                20.0,
                20.0,
                39.9994687,
                0.0005313,
                20.0
            ],
            "ratio": 0.0005209808645221982
        },
        {
            "input": 8000.0,
            "output": 4.167767409558932,
            "distribution": [
                20.0,
                20.0,
                39.9994687125,
                0.0005312875,
                20.0
            ],
            "ratio": 0.0005209709261948665
        },
        {
            "input": 10000.0,
            "output": 5.20960988738809,
            "distribution": [
                20.0,
                20.0,
                39.99946873,
                0.00053127,
                20.0
            ],
            "ratio": 0.0005209609887388089
        },
        {
            "input": 12000.0,
            "output": 6.251412625897478,
            "distribution": [
                20.0,
                20.0,
                39.99946873333333,
                0.0005312666666666667,
                20.0
            ],
            "ratio": 0.0005209510521581232
        },
        {
            "input": 14000.0,
            "output": 7.293175630893995,
            "distribution": [
                20.0,
                20.0,
                39.99946874285714,
                0.0005312571428571428,
                20.0
            ],
            "ratio": 0.0005209411164924281
        },
        {
            "input": 16000.0,
            "output": 8.334898906086995,
            "distribution": [
                20.0,
                20.0,
                39.99946874375,
                0.00053125625,
                20.0
            ],
            "ratio": 0.0005209311816304371
        },
        {
            "input": 18000.0,
            "output": 9.376582458318918,
            "distribution": [
                20.0,
                20.0,
                39.99946875,
                0.00053125,
                20.0
            ],
            "ratio": 0.0005209212476843843
        },
        {
            "input": 20000.0,
            "output": 10.418226292862654,
            "distribution": [
                20.0,
                20.0,
                39.99946875,
                0.00053125,
                20.0
            ],
            "ratio": 0.0005209113146431327
        },
        {
            "input": 22000.0,
            "output": 11.459830413955668,
            "distribution": [
                20.0,
                20.0,
                39.999468754545454,
                0.0005312454545454545,
                20.0
            ],
            "ratio": 0.0005209013824525304
        },
        {
            "input": 24000.0,
            "output": 12.501394827387646,
            "distribution": [
                20.0,
                20.0,
                39.999468754166664,
                0.0005312458333333333,
                20.0
            ],
            "ratio": 0.0005208914511411519
        },
        {
            "input": 26000.0,
            "output": 13.542919538440808,
            "distribution": [
                20.0,
                20.0,
                39.999468757692306,
                0.0005312423076923077,
                20.0
            ],
            "ratio": 0.0005208815207092619
        },
        {
            "input": 28000.0,
            "output": 14.584404552374922,
            "distribution": [
                20.0,
                20.0,
                39.99946875714286,
                0.0005312428571428571,
                20.0
            ],
            "ratio": 0.0005208715911562472
        },
        {
            "input": 30000.0,
            "output": 15.625849874470239,
            "distribution": [
                20.0,
                20.0,
                39.99946876,
                0.00053124,
                20.0
            ],
            "ratio": 0.0005208616624823413
        },
        {
            "input": 32000.0,
            "output": 16.6672555099907,
            "distribution": [
                20.0,
                20.0,
                39.999468759375,
                0.000531240625,
                20.0
            ],
            "ratio": 0.0005208517346872094
        },
        {
            "input": 34000.0,
            "output": 17.708621464211525,
            "distribution": [
                20.0,
                20.0,
                39.99946875882353,
                0.0005312411764705883,
                20.0
            ],
            "ratio": 0.0005208418077709272
        },
        {
            "input": 36000.0,
            "output": 18.7499477423947,
            "distribution": [
                20.0,
                20.0,
                39.999468758333336,
                0.0005312416666666666,
                20.0
            ],
            "ratio": 0.0005208318817331861
        },
        {
            "input": 38000.0,
            "output": 19.791234349816538,
            "distribution": [
                20.0,
                20.0,
                39.99946876315789,
                0.0005312368421052632,
                20.0
            ],
            "ratio": 0.0005208219565741194
        },
        {
            "input": 40000.0,
            "output": 20.8324812922497,
            "distribution": [
                20.0,
                20.0,
                39.99946876,
                0.00053124,
                20.0
            ],
            "ratio": 0.0005208120323062425
        },
        {
            "input": 42000.0,
            "output": 21.873688573412263,
            "distribution": [
                20.0,
                20.0,
                39.999468761904765,
                0.0005312380952380953,
                20.0
            ],
            "ratio": 0.0005208021088907682
        },
        {
            "input": 44000.0,
            "output": 22.914856200115516,
            "distribution": [
                20.0,
                20.0,
                39.99946875909091,
                0.0005312409090909091,
                20.0
            ],
            "ratio": 0.0005207921863662618
        },
        {
            "input": 46000.0,
            "output": 23.95598417764101,
            "distribution": [
                20.0,
                20.0,
                39.99946876304348,
                0.0005312369565217391,
                20.0
            ],
            "ratio": 0.0005207822647313263
        },
        {
            "input": 48000.0,
            "output": 24.99707251019207,
            "distribution": [
                20.0,
                20.0,
                39.9994687625,
                0.0005312375,
                20.0
            ],
            "ratio": 0.0005207723439623347
        },
        {
            "input": 50000.0,
            "output": 26.03812120304216,
            "distribution": [
                20.0,
                20.0,
                39.999468764,
                0.000531236,
                20.0
            ],
            "ratio": 0.0005207624240608432
        },
        {
            "input": 52000.0,
            "output": 27.07913026300478,
            "distribution": [
                20.0,
                20.0,
                39.999468763461536,
                0.0005312365384615384,
                20.0
            ],
            "ratio": 0.0005207525050577842
        },
        {
            "input": 54000.0,
            "output": 28.1200996937799,
            "distribution": [
                20.0,
                20.0,
                39.99946876296296,
                0.000531237037037037,
                20.0
            ],
            "ratio": 0.00052074258692185
        },
        {
            "input": 56000.0,
            "output": 29.16102950115373,
            "distribution": [
                20.0,
                20.0,
                39.99946876607143,
                0.0005312339285714286,
                20.0
            ],
            "ratio": 0.0005207326696634595
        },
        {
            "input": 58000.0,
            "output": 30.20191969037447,
            "distribution": [
                20.0,
                20.0,
                39.99946876551724,
                0.0005312344827586207,
                20.0
            ],
            "ratio": 0.0005207227532823184
        },
        {
            "input": 60000.0,
            "output": 31.242770266695437,
            "distribution": [
                20.0,
                20.0,
                39.99946876333333,
                0.0005312366666666667,
                20.0
            ],
            "ratio": 0.0005207128377782574
        },
        {
            "input": 62000.0,
            "output": 32.28358123538724,
            "distribution": [
                20.0,
                20.0,
                39.999468766129034,
                0.0005312338709677419,
                20.0
            ],
            "ratio": 0.000520702923151407
        },
        {
            "input": 64000.0,
            "output": 33.32435260168601,
            "distribution": [
                20.0,
                20.0,
                39.9994687640625,
                0.0005312359375,
                20.0
            ],
            "ratio": 0.0005206930094013439
        },
        {
            "input": 66000.0,
            "output": 34.36508437086648,
            "distribution": [
                20.0,
                20.0,
                39.999468766666666,
                0.0005312333333333334,
                20.0
            ],
            "ratio": 0.0005206830965282799
        },
        {
            "input": 68000.0,
            "output": 35.40577654736221,
            "distribution": [
                20.0,
                20.0,
                39.99946876470588,
                0.000531235294117647,
                20.0
            ],
            "ratio": 0.0005206731845200324
        },
        {
            "input": 70000.0,
            "output": 36.446429138035136,
            "distribution": [
                20.0,
                20.0,
                39.99946876714286,
                0.0005312328571428571,
                20.0
            ],
            "ratio": 0.000520663273400502
        },
        {
            "input": 72000.0,
            "output": 37.48704214784165,
            "distribution": [
                20.0,
                20.0,
                39.99946876388889,
                0.0005312361111111111,
                20.0
            ],
            "ratio": 0.0005206533631644673
        },
        {
            "input": 74000.0,
            "output": 38.527615580490185,
            "distribution": [
                20.0,
                20.0,
                39.999468764864865,
                0.0005312351351351351,
                20.0
            ],
            "ratio": 0.0005206434537904079
        },
        {
            "input": 76000.0,
            "output": 39.56814944278253,
            "distribution": [
                20.0,
                20.0,
                39.99946876710526,
                0.0005312328947368421,
                20.0
            ],
            "ratio": 0.00052063354529977
        },
        {
            "input": 78000.0,
            "output": 40.608643739960165,
            "distribution": [
                20.0,
                20.0,
                39.999468766666666,
                0.0005312333333333334,
                20.0
            ],
            "ratio": 0.0005206236376917969
        },
        {
            "input": 80000.0,
            "output": 41.64909847622915,
            "distribution": [
                20.0,
                20.0,
                39.999468765,
                0.000531235,
                20.0
            ],
            "ratio": 0.0005206137309528644
        },
        {
            "input": 82000.0,
            "output": 42.68951365685025,
            "distribution": [
                20.0,
                20.0,
                39.99946876707317,
                0.0005312329268292683,
                20.0
            ],
            "ratio": 0.0005206038250835397
        },
        {
            "input": 84000.0,
            "output": 43.72988928860923,
            "distribution": [
                20.0,
                20.0,
                39.99946876547619,
                0.0005312345238095239,
                20.0
            ],
            "ratio": 0.0005205939201024908
        },
        {
            "input": 86000.0,
            "output": 44.770225375205605,
            "distribution": [
                20.0,
                20.0,
                39.99946876744186,
                0.0005312325581395349,
                20.0
            ],
            "ratio": 0.0005205840159907629
        },
        {
            "input": 88000.0,
            "output": 45.810521922385675,
            "distribution": [
                20.0,
                20.0,
                39.99946876590909,
                0.0005312340909090909,
                20.0
            ],
            "ratio": 0.0005205741127543826
        },
        {
            "input": 90000.0,
            "output": 46.85077893541235,
            "distribution": [
                20.0,
                20.0,
                39.99946876777778,
                0.0005312322222222223,
                20.0
            ],
            "ratio": 0.0005205642103934706
        },
        {
            "input": 92000.0,
            "output": 47.890996419505186,
            "distribution": [
                20.0,
                20.0,
                39.999468767391306,
                0.0005312326086956521,
                20.0
            ],
            "ratio": 0.0005205543089076651
        },
        {
            "input": 94000.0,
            "output": 48.93117437991606,
            "distribution": [
                20.0,
                20.0,
                39.99946876808511,
                0.000531231914893617,
                20.0
            ],
            "ratio": 0.0005205444082969794
        },
        {
            "input": 96000.0,
            "output": 49.97131282187468,
            "distribution": [
                20.0,
                20.0,
                39.999468766666666,
                0.0005312333333333334,
                20.0
            ],
            "ratio": 0.0005205345085611946
        },
        {
            "input": 98000.0,
            "output": 51.011411750634004,
            "distribution": [
                20.0,
                20.0,
                39.99946876734694,
                0.0005312326530612245,
                20.0
            ],
            "ratio": 0.000520524609700347
        },
        {
            "input": 100000.0,
            "output": 52.051471171418775,
            "distribution": [
                20.0,
                20.0,
                39.999468768,
                0.000531232,
                20.0
            ],
            "ratio": 0.0005205147117141877
        },
        {
            "input": 102000.0,
            "output": 53.09149108946487,
            "distribution": [
                20.0,
                20.0,
                39.99946876764706,
                0.0005312323529411765,
                20.0
            ],
            "ratio": 0.0005205048146025967
        },
        {
            "input": 104000.0,
            "output": 54.13147151053199,
            "distribution": [
                20.0,
                20.0,
                39.99946876730769,
                0.0005312326923076923,
                20.0
            ],
            "ratio": 0.0005204949183704999
        },
        {
            "input": 106000.0,
            "output": 55.17141243829778,
            "distribution": [
                20.0,
                20.0,
                39.99946876886793,
                0.0005312311320754717,
                20.0
            ],
            "ratio": 0.0005204850230028092
        },
        {
            "input": 108000.0,
            "output": 56.21131387954243,
            "distribution": [
                20.0,
                20.0,
                39.99946876851852,
                0.0005312314814814815,
                20.0
            ],
            "ratio": 0.0005204751285142817
        },
        {
            "input": 110000.0,
            "output": 57.251175839500945,
            "distribution": [
                20.0,
                20.0,
                39.999468766363634,
                0.0005312336363636364,
                20.0
            ],
            "ratio": 0.000520465234904554
        },
        {
            "input": 112000.0,
            "output": 58.29099832237887,
            "distribution": [
                20.0,
                20.0,
                39.999468767857145,
                0.0005312321428571429,
                20.0
            ],
            "ratio": 0.000520455342164097
        },
        {
            "input": 114000.0,
            "output": 59.33078133339418,
            "distribution": [
                20.0,
                20.0,
                39.99946876842105,
                0.0005312315789473684,
                20.0
            ],
            "ratio": 0.0005204454502929313
        },
        {
            "input": 116000.0,
            "output": 60.37052487933224,
            "distribution": [
                20.0,
                20.0,
                39.99946876724138,
                0.0005312327586206897,
                20.0
            ],
            "ratio": 0.0005204355593045882
        },
        {
            "input": 118000.0,
            "output": 61.410228963873884,
            "distribution": [
                20.0,
                20.0,
                39.99946876864407,
                0.0005312313559322034,
                20.0
            ],
            "ratio": 0.0005204256691853719
        },
        {
            "input": 120000.0,
            "output": 62.44989359275598,
            "distribution": [
                20.0,
                20.0,
                39.99946876916667,
                0.0005312308333333334,
                20.0
            ],
            "ratio": 0.0005204157799396332
        },
        {
            "input": 122000.0,
            "output": 63.48951877120168,
            "distribution": [
                20.0,
                20.0,
                39.999468767213116,
                0.000531232786885246,
                20.0
            ],
            "ratio": 0.0005204058915672269
        },
        {
            "input": 124000.0,
            "output": 64.52910450445118,
            "distribution": [
                20.0,
                20.0,
                39.99946876854839,
                0.0005312314516129033,
                20.0
            ],
            "ratio": 0.0005203960040681548
        },
        {
            "input": 126000.0,
            "output": 65.5686507977137,
            "distribution": [
                20.0,
                20.0,
                39.99946876825397,
                0.000531231746031746,
                20.0
            ],
            "ratio": 0.0005203861174421723
        },
        {
            "input": 128000.0,
            "output": 66.60815765621847,
            "distribution": [
                20.0,
                20.0,
                39.99946876796875,
                0.00053123203125,
                20.0
            ],
            "ratio": 0.0005203762316892068
        },
        {
            "input": 130000.0,
            "output": 67.64762508571553,
            "distribution": [
                20.0,
                20.0,
                39.999468769230766,
                0.0005312307692307692,
                20.0
            ],
            "ratio": 0.0005203663468131964
        },
        {
            "input": 132000.0,
            "output": 68.6870530898489,
            "distribution": [
                20.0,
                20.0,
                39.99946876818182,
                0.0005312318181818182,
                20.0
            ],
            "ratio": 0.0005203564628018856
        },
        {
            "input": 134000.0,
            "output": 69.7264416754132,
            "distribution": [
                20.0,
                20.0,
                39.99946876865672,
                0.0005312313432835821,
                20.0
            ],
            "ratio": 0.0005203465796672627
        },
        {
            "input": 136000.0,
            "output": 70.76579084762179,
            "distribution": [
                20.0,
                20.0,
                39.99946876838235,
                0.0005312316176470588,
                20.0
            ],
            "ratio": 0.0005203366974089837
        },
        {
            "input": 138000.0,
            "output": 71.80510061065553,
            "distribution": [
                20.0,
                20.0,
                39.99946876884058,
                0.0005312311594202899,
                20.0
            ],
            "ratio": 0.000520326816019243
        },
        {
            "input": 140000.0,
            "output": 72.8443709697289,
            "distribution": [
                20.0,
                20.0,
                39.999468768571425,
                0.0005312314285714285,
                20.0
            ],
            "ratio": 0.0005203169354980636
        },
        {
            "input": 142000.0,
            "output": 73.88360193162356,
            "distribution": [
                20.0,
                20.0,
                39.999468769014086,
                0.000531230985915493,
                20.0
            ],
            "ratio": 0.000520307055856504
        },
        {
            "input": 144000.0,
            "output": 74.92279349998678,
            "distribution": [
                20.0,
                20.0,
                39.99946876875,
                0.00053123125,
                20.0
            ],
            "ratio": 0.0005202971770832416
        },
        {
            "input": 146000.0,
            "output": 75.96194568055785,
            "distribution": [
                20.0,
                20.0,
                39.99946876849315,
                0.0005312315068493151,
                20.0
            ],
            "ratio": 0.000520287299181903
        },
        {
            "input": 148000.0,
            "output": 77.00105847855926,
            "distribution": [
                20.0,
                20.0,
                39.99946876959459,
                0.0005312304054054054,
                20.0
            ],
            "ratio": 0.0005202774221524275
        },
        {
            "input": 150000.0,
            "output": 78.04013189918567,
            "distribution": [
                20.0,
                20.0,
                39.99946876933333,
                0.0005312306666666667,
                20.0
            ],
            "ratio": 0.0005202675459945711
        },
        {
            "input": 152000.0,
            "output": 79.07916594765466,
            "distribution": [
                20.0,
                20.0,
                39.99946876842105,
                0.0005312315789473684,
                20.0
            ],
            "ratio": 0.0005202576707082542
        },
        {
            "input": 154000.0,
            "output": 80.1181606297076,
            "distribution": [
                20.0,
                20.0,
                39.99946876883117,
                0.0005312311688311688,
                20.0
            ],
            "ratio": 0.0005202477962968026
        },
        {
            "input": 156000.0,
            "output": 81.15711594898598,
            "distribution": [
                20.0,
                20.0,
                39.999468769230766,
                0.0005312307692307692,
                20.0
            ],
            "ratio": 0.00052023792274991
        },
        {
            "input": 158000.0,
            "output": 82.19603191225477,
            "distribution": [
                20.0,
                20.0,
                39.99946876898734,
                0.0005312310126582278,
                20.0
            ],
            "ratio": 0.0005202280500775617
        },
        {
            "input": 160000.0,
            "output": 83.23490852420892,
            "distribution": [
                20.0,
                20.0,
                39.999468769375,
                0.000531230625,
                20.0
            ],
            "ratio": 0.0005202181782763056
        },
        {
            "input": 162000.0,
            "output": 84.27374579057398,
            "distribution": [
                20.0,
                20.0,
                39.999468769753086,
                0.0005312302469135802,
                20.0
            ],
            "ratio": 0.0005202083073492221
        },
        {
            "input": 164000.0,
            "output": 85.31254371499055,
            "distribution": [
                20.0,
                20.0,
                39.9994687695122,
                0.000531230487804878,
                20.0
            ],
            "ratio": 0.0005201984372865278
        },
        {
            "input": 166000.0,
            "output": 86.35130230422574,
            "distribution": [
                20.0,
                20.0,
                39.99946876927711,
                0.0005312307228915663,
                20.0
            ],
            "ratio": 0.0005201885680977455
        },
        {
            "input": 168000.0,
            "output": 87.39002156348937,
            "distribution": [
                20.0,
                20.0,
                39.99946876964286,
                0.0005312303571428571,
                20.0
            ],
            "ratio": 0.0005201786997826748
        },
        {
            "input": 170000.0,
            "output": 88.42870149693196,
            "distribution": [
                20.0,
                20.0,
                39.999468768823526,
                0.0005312311764705882,
                20.0
            ],
            "ratio": 0.0005201688323348938
        },
        {
            "input": 172000.0,
            "output": 89.46734210977336,
            "distribution": [
                20.0,
                20.0,
                39.99946876976744,
                0.0005312302325581396,
                20.0
            ],
            "ratio": 0.0005201589657544963
        },
        {
            "input": 174000.0,
            "output": 90.50594340875887,
            "distribution": [
                20.0,
                20.0,
                39.99946876954023,
                0.0005312304597701149,
                20.0
            ],
            "ratio": 0.0005201491000503384
        },
        {
            "input": 176000.0,
            "output": 91.54450539753525,
            "distribution": [
                20.0,
                20.0,
                39.99946876988636,
                0.0005312301136363636,
                20.0
            ],
            "ratio": 0.0005201392352132683
        },
        {
            "input": 178000.0,
            "output": 92.58302808181733,
            "distribution": [
                20.0,
                20.0,
                39.99946876966292,
                0.0005312303370786517,
                20.0
            ],
            "ratio": 0.0005201293712461647
        },
        {
            "input": 180000.0,
            "output": 93.62151146681218,
            "distribution": [
                20.0,
                20.0,
                39.99946877,
                0.00053123,
                20.0
            ],
            "ratio": 0.0005201195081489566
        },
        {
            "input": 182000.0,
            "output": 94.65995555770202,
            "distribution": [
                20.0,
                20.0,
                39.999468769230766,
                0.0005312307692307692,
                20.0
            ],
            "ratio": 0.0005201096459214396
        },
        {
            "input": 184000.0,
            "output": 95.69836035969789,
            "distribution": [
                20.0,
                20.0,
                39.99946876956522,
                0.0005312304347826087,
                20.0
            ],
            "ratio": 0.0005200997845635755
        },
        {
            "input": 186000.0,
            "output": 96.73672587851377,
            "distribution": [
                20.0,
                20.0,
                39.999468770430106,
                0.0005312295698924731,
                20.0
            ],
            "ratio": 0.000520089924078031
        },
        {
            "input": 188000.0,
            "output": 97.77505211776977,
            "distribution": [
                20.0,
                20.0,
                39.99946876968085,
                0.0005312303191489362,
                20.0
            ],
            "ratio": 0.0005200800644562223
        },
        {
            "input": 190000.0,
            "output": 98.81333908423035,
            "distribution": [
                20.0,
                20.0,
                39.99946876947369,
                0.0005312305263157895,
                20.0
            ],
            "ratio": 0.0005200702057064755
        },
        {
            "input": 192000.0,
            "output": 99.85158678257197,
            "distribution": [
                20.0,
                20.0,
                39.9994687703125,
                0.0005312296875,
                20.0
            ],
            "ratio": 0.0005200603478258956
        },
        {
            "input": 194000.0,
            "output": 100.88979521848995,
            "distribution": [
                20.0,
                20.0,
                39.999468769072166,
                0.0005312309278350516,
                20.0
            ],
            "ratio": 0.0005200504908169585
        },
        {
            "input": 196000.0,
            "output": 101.92796439563323,
            "distribution": [
                20.0,
                20.0,
                39.999468769387754,
                0.000531230612244898,
                20.0
            ],
            "ratio": 0.0005200406346715981
        },
        {
            "input": 198000.0,
            "output": 102.96609432074455,
            "distribution": [
                20.0,
                20.0,
                39.99946877020202,
                0.0005312297979797979,
                20.0
            ],
            "ratio": 0.0005200307793976998
        },
        {
            "input": 200000.0,
            "output": 104.00418499900643,
            "distribution": [
                20.0,
                20.0,
                39.99946877,
                0.00053123,
                20.0
            ],
            "ratio": 0.000520020924995032
        },
        {
            "input": 200000.0,
            "output": 104.00418499900643,
            "distribution": [
                20.0,
                20.0,
                39.99946877,
                0.00053123,
                20.0
            ],
            "ratio": 0.000520020924995032
        },
        {
            "input": 250000.0,
            "output": 129.94371170649842,
            "distribution": [
                20.0,
                20.0,
                39.99946877,
                0.00053123,
                20.0
            ],
            "ratio": 0.0005197748468259936
        },
        {
            "input": 300000.0,
            "output": 155.85879288114035,
            "distribution": [
                20.0,
                20.0,
                39.999468771,
                0.000531229,
                20.0
            ],
            "ratio": 0.0005195293096038011
        },
        {
            "input": 350000.0,
            "output": 181.95894917776963,
            "distribution": [
                20.0,
                16.2,
                47.59919032342857,
                0.0008096765714285714,
                16.2
            ],
            "ratio": 0.0005198827119364846
        },
        {
            "input": 400000.0,
            "output": 207.98470463948817,
            "distribution": [
                20.0,
                14.58,
                50.8390003995,
                0.0009996005,
                14.58
            ],
            "ratio": 0.0005199617615987204
        },
        {
            "input": 450000.0,
            "output": 234.02029704409495,
            "distribution": [
                20.0,
                13.122,
                53.754765926,
                0.001234074,
                13.122
            ],
            "ratio": 0.0005200451045424332
        },
        {
            "input": 500000.0,
            "output": 260.0635373268406,
            "distribution": [
                20.0,
                11.8098,
                56.378876452,
                0.001523548,
                11.8098
            ],
            "ratio": 0.0005201270746536811
        },
        {
            "input": 550000.0,
            "output": 286.1122032884841,
            "distribution": [
                20.0,
                10.62882,
                58.74047907690909,
                0.0018809230909090909,
                10.62882
            ],
            "ratio": 0.0005202040059790621
        },
        {
            "input": 600000.0,
            "output": 312.1642055547229,
            "distribution": [
                20.0,
                9.565938,
                60.865801873,
                0.002322127,
                9.565938
            ],
            "ratio": 0.0005202736759245383
        },
        {
            "input": 650000.0,
            "output": 338.13083352676125,
            "distribution": [
                20.0,
                9.565938,
                60.86580187323077,
                0.0023221267692307692,
                9.565938
            ],
            "ratio": 0.0005202012823488634
        },
        {
            "input": 700000.0,
            "output": 364.19023339140404,
            "distribution": [
                20.0,
                8.6093442,
                62.778444777,
                0.002866823,
                8.6093442
            ],
            "ratio": 0.00052027176198772
        },
        {
            "input": 750000.0,
            "output": 390.24857923092776,
            "distribution": [
                20.0,
                7.74840978,
                64.49964115253333,
                0.0035392874666666666,
                7.74840978
            ],
            "ratio": 0.0005203314389745703
        },
        {
            "input": 800000.0,
            "output": 416.2205963215081,
            "distribution": [
                20.0,
                7.74840978,
                64.499641152625,
                0.003539287375,
                7.74840978
            ],
            "ratio": 0.000520275745401885
        },
        {
            "input": 850000.0,
            "output": 442.28125330487774,
            "distribution": [
                20.0,
                6.973568802,
                66.04849290541176,
                0.004369490588235294,
                6.973568802
            ],
            "ratio": 0.0005203308862410327
        },
        {
            "input": 900000.0,
            "output": 468.2529976527133,
            "distribution": [
                20.0,
                6.973568802,
                66.04849290544445,
                0.004369490555555556,
                6.973568802
            ],
            "ratio": 0.0005202811085030148
        },
        {
            "input": 950000.0,
            "output": 494.3134290042948,
            "distribution": [
                20.0,
                6.2762119218947365,
                67.44218172368421,
                0.00539443252631579,
                6.2762119218947365
            ],
            "ratio": 0.0005203299252676787
        },
        {
            "input": 1000000.0,
            "output": 520.284847918962,
            "distribution": [
                20.0,
                6.2762119218,
                67.4421817238,
                0.0053944326,
                6.2762119218
            ],
            "ratio": 0.0005202848479189619
        },
        {
            "input": 1050000.0,
            "output": 546.342730711922,
            "distribution": [
                20.0,
                5.648590729714286,
                68.69615874742857,
                0.006659793142857143,
                5.648590729714286
            ],
            "ratio": 0.0005203264102018304
        },
        {
            "input": 1100000.0,
            "output": 572.3135660035515,
            "distribution": [
                20.0,
                5.648590729636363,
                68.69615874754545,
                0.006659793181818182,
                5.648590729636363
            ],
            "ratio": 0.0005202850600032286
        },
        {
            "input": 1150000.0,
            "output": 598.3668872748739,
            "distribution": [
                20.0,
                5.083731656695652,
                69.82431471982609,
                0.008221966782608696,
                5.083731656695652
            ],
            "ratio": 0.0005203190324129338
        },
        {
            "input": 1200000.0,
            "output": 624.3367567354602,
            "distribution": [
                20.0,
                5.08373165675,
                69.82431471983334,
                0.008221966666666667,
                5.08373165675
            ],
            "ratio": 0.0005202806306128836
        },
        {
            "input": 1250000.0,
            "output": 650.3027999308675,
            "distribution": [
                20.0,
                5.08373165672,
                69.82431471992,
                0.00822196664,
                5.08373165672
            ],
            "ratio": 0.0005202422399446941
        },
        {
            "input": 1300000.0,
            "output": 676.3523036797482,
            "distribution": [
                20.0,
                4.575358491153846,
                70.83913244161539,
                0.010150576076923077,
                4.575358491153846
            ],
            "ratio": 0.0005202710028305756
        },
        {
            "input": 1350000.0,
            "output": 702.3171629912412,
            "distribution": [
                20.0,
                4.575358491111111,
                70.8391324417037,
                0.010150576074074075,
                4.575358491111111
            ],
            "ratio": 0.0005202349355490675
        },
        {
            "input": 1400000.0,
            "output": 728.2784279480728,
            "distribution": [
                20.0,
                4.5753584911428575,
                70.83913244171428,
                0.010150576,
                4.5753584911428575
            ],
            "ratio": 0.0005201988771057663
        },
        {
            "input": 1450000.0,
            "output": 754.3215579637083,
            "distribution": [
                20.0,
                4.117822642,
                71.75182314075862,
                0.01253157524137931,
                4.117822642
            ],
            "ratio": 0.0005202217641129024
        },
        {
            "input": 1500000.0,
            "output": 780.2812959572033,
            "distribution": [
                20.0,
                4.117822642,
                71.75182314066667,
                0.012531575333333333,
                4.117822642
            ],
            "ratio": 0.0005201875306381355
        },
        {
            "input": 1550000.0,
            "output": 806.2376217377829,
            "distribution": [
                20.0,
                4.117822642,
                71.75182314070967,
                0.01253157529032258,
                4.117822642
            ],
            "ratio": 0.0005201533043469567
        },
        {
            "input": 1600000.0,
            "output": 832.2721726215765,
            "distribution": [
                20.0,
                3.706040377875,
                72.5724481638125,
                0.0154710804375,
                3.706040377875
            ],
            "ratio": 0.0005201701078884853
        },
        {
            "input": 1650000.0,
            "output": 858.226560653811,
            "distribution": [
                20.0,
                3.706040377818182,
                72.5724481639394,
                0.015471080424242424,
                3.706040377818182
            ],
            "ratio": 0.0005201373094871582
        },
        {
            "input": 1700000.0,
            "output": 884.1776790278353,
            "distribution": [
                20.0,
                3.7060403778235296,
                72.57244816388236,
                0.015471080470588235,
                3.7060403778235296
            ],
            "ratio": 0.0005201045170751973
        },
        {
            "input": 1750000.0,
            "output": 910.1255286379272,
            "distribution": [
                20.0,
                3.7060403778285713,
                72.57244816382857,
                0.015471080514285715,
                3.7060403778285713
            ],
            "ratio": 0.0005200717306502441
        },
        {
            "input": 1800000.0,
            "output": 936.1101868867083,
            "distribution": [
                20.0,
                3.7060403778333333,
                72.94133319272223,
                0.01719008938888889,
                3.3354363400555553
            ],
            "ratio": 0.0005200612149370602
        },
        {
            "input": 1850000.0,
            "output": 962.0961650296784,
            "distribution": [
                20.0,
                3.335436340054054,
                73.31002722070271,
                0.019100099189189187,
                3.335436340054054
            ],
            "ratio": 0.0005200519810971235
        },
        {
            "input": 1900000.0,
            "output": 988.0385930843684,
            "distribution": [
                20.0,
                3.335436340105263,
                73.31002722052632,
                0.019100099263157894,
                3.335436340105263
            ],
            "ratio": 0.0005200203121496676
        },
        {
            "input": 1950000.0,
            "output": 1013.9778651238437,
            "distribution": [
                20.0,
                3.335436340102564,
                73.31002722056411,
                0.019100099230769232,
                3.335436340102564
            ],
            "ratio": 0.0005199886487814582
        },
        {
            "input": 2000000.0,
            "output": 1039.9139819160225,
            "distribution": [
                20.0,
                3.33543634005,
                73.31002722065,
                0.01910009925,
                3.33543634005
            ],
            "ratio": 0.0005199569909580112
        },
        {
            "input": 2000000.0,
            "output": 1039.9139819160225,
            "distribution": [
                20.0,
                3.33543634005,
                73.31002722065,
                0.01910009925,
                3.33543634005
            ],
            "ratio": 0.0005199569909580112
        },
        {
            "input": 4000000.0,
            "output": 2075.6437845575883,
            "distribution": [
                20.0,
                2.1883797827,
                75.792777718625,
                0.049300694225,
                1.96954180445
            ],
            "ratio": 0.0005189109461393971
        },
        {
            "input": 6000000.0,
            "output": 3106.8240892452764,
            "distribution": [
                22.021547390966667,
                1.7725876239833334,
                74.36564952271667,
                0.06762783835,
                1.7725876239833334
            ],
            "ratio": 0.0005178040148742127
        },
        {
            "input": 8000000.0,
            "output": 4133.655614225352,
            "distribution": [
                23.06348046145,
                1.595328861575,
                73.6623706569875,
                0.0834911584125,
                1.595328861575
            ],
            "ratio": 0.0005167069517781691
        },
        {
            "input": 10000000.0,
            "output": 5156.088145260676,
            "distribution": [
                23.97987817547,
                1.59532886157,
                72.89622903376,
                0.09276795378,
                1.43579597542
            ],
            "ratio": 0.0005156088145260677
        },
        {
            "input": 12000000.0,
            "output": 6174.056692382934,
            "distribution": [
                24.4398346495,
                1.5953288615666668,
                72.43627255975,
                0.09276795376666666,
                1.4357959754166667
            ],
            "ratio": 0.0005145047243652445
        },
        {
            "input": 14000000.0,
            "output": 7187.657038032674,
            "distribution": [
                24.899126058642857,
                1.59532886155,
                71.97698115064286,
                0.09276795376428572,
                1.4357959754
            ],
            "ratio": 0.000513404074145191
        },
        {
            "input": 16000000.0,
            "output": 8197.146086671504,
            "distribution": [
                25.07722387359375,
                1.4357959754,
                71.94810867143126,
                0.103075504175,
                1.4357959754
            ],
            "ratio": 0.000512321630416969
        },
        {
            "input": 18000000.0,
            "output": 9202.224698384452,
            "distribution": [
                25.272526615694446,
                1.4357959754,
                71.75280592933333,
                0.10307550417222222,
                1.4357959754
            ],
            "ratio": 0.0005112347054658029
        },
        {
            "input": 20000000.0,
            "output": 10203.09242524076,
            "distribution": [
                25.41251168033,
                1.4357959754,
                71.6128208647,
                0.10307550417,
                1.4357959754
            ],
            "ratio": 0.000510154621262038
        },
        {
            "input": 22000000.0,
            "output": 11199.799177953757,
            "distribution": [
                25.530478682495456,
                1.4357959754,
                71.49485386254091,
                0.10307550416363637,
                1.4357959754
            ],
            "ratio": 0.00050908178081608
        },
        {
            "input": 24000000.0,
            "output": 12192.38383046025,
            "distribution": [
                25.711101572154167,
                1.4357959754,
                71.31423097288334,
                0.1030755041625,
                1.4357959754
            ],
            "ratio": 0.0005080159929358438
        },
        {
            "input": 26000000.0,
            "output": 13180.868452594821,
            "distribution": [
                25.81945433796923,
                1.4357959754,
                71.20587820706538,
                0.10307550416538462,
                1.4357959754
            ],
            "ratio": 0.0005069564789459546
        },
        {
            "input": 28000000.0,
            "output": 14165.278339534667,
            "distribution": [
                25.893802502132143,
                1.4357959753964287,
                71.13153004291071,
                0.10307550416428571,
                1.4357959753964287
            ],
            "ratio": 0.0005059027978405238
        },
        {
            "input": 30000000.0,
            "output": 15145.287127242917,
            "distribution": [
                26.138758689303334,
                1.4357959753933334,
                70.88657385575333,
                0.10307550415666666,
                1.4357959753933334
            ],
            "ratio": 0.0005048429042414306
        },
        {
            "input": 32000000.0,
            "output": 16120.689599032052,
            "distribution": [
                26.522996676721874,
                1.43579597539375,
                70.50233586833124,
                0.103075504159375,
                1.43579597539375
            ],
            "ratio": 0.0005037715499697517
        },
        {
            "input": 34000000.0,
            "output": 17091.524545955046,
            "distribution": [
                26.78525736987353,
                1.4357959753941176,
                70.24007517517647,
                0.10307550416176471,
                1.4357959753941176
            ],
            "ratio": 0.0005026918984104426
        },
        {
            "input": 36000000.0,
            "output": 18057.831882424227,
            "distribution": [
                26.94741568491111,
                1.4357959753972223,
                70.07791686013611,
                0.10307550415833333,
                1.4357959753972223
            ],
            "ratio": 0.0005016064411784508
        },
        {
            "input": 38000000.0,
            "output": 19019.642236773147,
            "distribution": [
                27.199685702947367,
                1.4357959753921052,
                69.82564684211053,
                0.10307550415789474,
                1.4357959753921052
            ],
            "ratio": 0.0005005169009677144
        },
        {
            "input": 40000000.0,
            "output": 19976.99594337689,
            "distribution": [
                27.38653138083,
                1.435795975395,
                69.6388011642225,
                0.1030755041575,
                1.435795975395
            ],
            "ratio": 0.0004994248985844222
        },
        {
            "input": 42000000.0,
            "output": 20929.92521770063,
            "distribution": [
                27.550897729669046,
                1.435795975395238,
                69.47443481538333,
                0.10307550415714285,
                1.435795975395238
            ],
            "ratio": 0.0004983315528023961
        },
        {
            "input": 44000000.0,
            "output": 21878.462767649857,
            "distribution": [
                27.65030383954318,
                1.435795975390909,
                69.37502870551818,
                0.10307550415681818,
                1.435795975390909
            ],
            "ratio": 0.0004972377901738604
        },
        {
            "input": 46000000.0,
            "output": 22822.642939027795,
            "distribution": [
                27.856501969519567,
                1.4357959753891305,
                69.16883057554783,
                0.10307550415434782,
                1.4357959753891305
            ],
            "ratio": 0.0004961444117179955
        },
        {
            "input": 48000000.0,
            "output": 23762.505681558276,
            "distribution": [
                27.991336876820835,
                1.4357959753895833,
                69.03399566824375,
                0.10307550415625,
                1.4357959753895833
            ],
            "ratio": 0.0004950522016991308
        },
        {
            "input": 20000000.0,
            "output": 10203.09242524076,
            "distribution": [
                25.41251168033,
                1.4357959754,
                71.6128208647,
                0.10307550417,
                1.4357959754
            ],
            "ratio": 0.000510154621262038
        }
    ],
    "pools": [
        {
            "address": "0x8ad599c3a0ff1de082011efddc58f1908eb6e6d8",
            "id": "0x8ad599c3a0ff1de082011efddc58f1908eb6e6d8",
            "tokens": [
                {
                    "address": "0xa0b86991c6218b36c1d19d4a2e9eb0ce3606eb48",
                    "decimals": 6,
                    "symbol": "USDC",
                    "gas": "0"
                },
                {
                    "address": "0xc02aaa39b223fe8d0a0e5c4f27ead9083c756cc2",
                    "decimals": 18,
                    "symbol": "WETH",
                    "gas": "0"
                }
            ],
            "protocol_system": "uniswap_v3",
            "protocol_type_name": "uniswap_v3_pool",
            "chain": "ethereum",
            "contract_ids": [],
            "static_attributes": [
                [
                    "fee",
                    "0x0bb8"
                ],
                [
                    "tick_spacing",
                    "0x3c"
                ],
                [
                    "pool_address",
                    "0x8ad599c3a0ff1de082011efddc58f1908eb6e6d8"
                ]
            ],
            "creation_tx": "0x89d75075eaef8c21ab215ae54144ba563b850ee7460f89b2a175fd0e267ed330",
            "created_at": "2021-05-04T23:10:00"
        },
        {
            "address": "0xb4e16d0168e52d35cacd2c6185b44281ec28c9dc",
            "id": "0xb4e16d0168e52d35cacd2c6185b44281ec28c9dc",
            "tokens": [
                {
                    "address": "0xa0b86991c6218b36c1d19d4a2e9eb0ce3606eb48",
                    "decimals": 6,
                    "symbol": "USDC",
                    "gas": "0"
                },
                {
                    "address": "0xc02aaa39b223fe8d0a0e5c4f27ead9083c756cc2",
                    "decimals": 18,
                    "symbol": "WETH",
                    "gas": "0"
                }
            ],
            "protocol_system": "uniswap_v2",
            "protocol_type_name": "uniswap_v2_pool",
            "chain": "ethereum",
            "contract_ids": [],
            "static_attributes": [
                [
                    "pool_address",
                    "0xb4e16d0168e52d35cacd2c6185b44281ec28c9dc"
                ],
                [
                    "fee",
                    "0x1e"
                ]
            ],
            "creation_tx": "0xd07cbde817318492092cc7a27b3064a69bd893c01cb593d6029683ffd290ab3a",
            "created_at": "2020-05-05T20:22:25"
        },
        {
            "address": "0x88e6a0c2ddd26feeb64f039a2c41296fcb3f5640",
            "id": "0x88e6a0c2ddd26feeb64f039a2c41296fcb3f5640",
            "tokens": [
                {
                    "address": "0xa0b86991c6218b36c1d19d4a2e9eb0ce3606eb48",
                    "decimals": 6,
                    "symbol": "USDC",
                    "gas": "0"
                },
                {
                    "address": "0xc02aaa39b223fe8d0a0e5c4f27ead9083c756cc2",
                    "decimals": 18,
                    "symbol": "WETH",
                    "gas": "0"
                }
            ],
            "protocol_system": "uniswap_v3",
            "protocol_type_name": "uniswap_v3_pool",
            "chain": "ethereum",
            "contract_ids": [],
            "static_attributes": [
                [
                    "fee",
                    "0x01f4"
                ],
                [
                    "pool_address",
                    "0x88e6a0c2ddd26feeb64f039a2c41296fcb3f5640"
                ],
                [
                    "tick_spacing",
                    "0x0a"
                ]
            ],
            "creation_tx": "0x125e0b641d4a4b08806bf52c0c6757648c9963bcda8681e4f996f09e00d4c2cc",
            "created_at": "2021-05-05T21:42:11"
        },
        {
            "address": "0x7bea39867e4169dbe237d55c8242a8f2fcdcc387",
            "id": "0x7bea39867e4169dbe237d55c8242a8f2fcdcc387",
            "tokens": [
                {
                    "address": "0xa0b86991c6218b36c1d19d4a2e9eb0ce3606eb48",
                    "decimals": 6,
                    "symbol": "USDC",
                    "gas": "0"
                },
                {
                    "address": "0xc02aaa39b223fe8d0a0e5c4f27ead9083c756cc2",
                    "decimals": 18,
                    "symbol": "WETH",
                    "gas": "0"
                }
            ],
            "protocol_system": "uniswap_v3",
            "protocol_type_name": "uniswap_v3_pool",
            "chain": "ethereum",
            "contract_ids": [],
            "static_attributes": [
                [
                    "fee",
                    "0x2710"
                ],
                [
                    "pool_address",
                    "0x7bea39867e4169dbe237d55c8242a8f2fcdcc387"
                ],
                [
                    "tick_spacing",
                    "0x00c8"
                ]
            ],
            "creation_tx": "0x004cb88319b0678320cb0a04fab8003897f33c345576adfbb1f79b903a0509f0",
            "created_at": "2021-05-04T20:07:45"
        },
        {
            "address": "0xe0554a476a092703abdb3ef35c80e0d76d32939f",
            "id": "0xe0554a476a092703abdb3ef35c80e0d76d32939f",
            "tokens": [
                {
                    "address": "0xa0b86991c6218b36c1d19d4a2e9eb0ce3606eb48",
                    "decimals": 6,
                    "symbol": "USDC",
                    "gas": "0"
                },
                {
                    "address": "0xc02aaa39b223fe8d0a0e5c4f27ead9083c756cc2",
                    "decimals": 18,
                    "symbol": "WETH",
                    "gas": "0"
                }
            ],
            "protocol_system": "uniswap_v3",
            "protocol_type_name": "uniswap_v3_pool",
            "chain": "ethereum",
            "contract_ids": [],
            "static_attributes": [
                [
                    "fee",
                    "0x64"
                ],
                [
                    "tick_spacing",
                    "0x01"
                ],
                [
                    "pool_address",
                    "0xe0554a476a092703abdb3ef35c80e0d76d32939f"
                ]
            ],
            "creation_tx": "0x9a773c2ab3acc47552e73d553b35e29c8fb0ca9576882f46552254232edb3cfd",
            "created_at": "2021-11-14T21:44:29"
        }
    ]
}